<?xml version="1.0" encoding="utf-8"?>
<!DOCTYPE I2CEConfiguration SYSTEM "I2CE_Configuration.dtd">
<I2CEConfiguration name="CustomReports">
  <metadata>
    <version>4.1.11.0.1</version>
  </metadata>
  <configurationGroup name="CustomReports" locale="nl">
    <version>4.1.9.0.1</version>
    <configurationGroup name="tasks" path="/modules/CustomReports/text/" locale="nl">
      <configuration name="Increasing">
        <value>Oplopend</value>
      </configuration>
      <configuration name="Decreasing">
        <value>Aflopend</value>
      </configuration>
      <configurationGroup name="user_messages">
        <configuration name="no_report_view">
          <value>U moet een rapportage opgeven die u wilt bekijken</value>
        </configuration>
        <configuration name="invalid_report_view">
          <value>U hebt een niet-bestaande rapportage opgegeven</value>
        </configuration>
        <configuration name="no_permission_report_view">
          <value>U hebt geen rechten om deze rapportage te bekijken</value>
        </configuration>
        <configuration name="no_display_report_view">
          <value>Het was niet mogelijk om geldige waarden in deze rapportage weer te geven</value>
        </configuration>
        <configuration name="reportView_merged_field_display">
          <value>%s van %s</value>
        </configuration>
        <configuration name="merge_display">
          <value>%s gekoppeld op %s</value>
        </configuration>
        <configurationGroup name="merge_descriptions">
          <configuration name="parent">
            <value>%s gekoppeld op %s als een bovenliggend formulier</value>
          </configuration>
          <configuration name="child">
            <value>%s gekoppeld op %s als een onderliggend formulier</value>
          </configuration>
          <configuration name="default">
            <value>%s gekoppeld op %s</value>
          </configuration>
        </configurationGroup>
        <configuration name="report_no_name">
          <value>Geen verkorte naam opgegeven voor de rapportage</value>
        </configuration>
        <configuration name="report_bad_name">
          <value>Ongeldige verkorte naam opgegeven voor de rapportage</value>
        </configuration>
        <configuration name="report_bad_used">
          <value>De opgegeven korte naam voor de rapportage is al in gebruik</value>
        </configuration>
        <configuration name="report_no_relationship">
          <value>Er is geen rapportagerelatie opgegeven voor de rapportage</value>
        </configuration>
        <configuration name="report_bad_relationship">
          <value>De opgegeven rapportagerelatie is ongeldig</value>
        </configuration>
        <configuration name="cannot_delete">
          <value>U hebt geen rechten om rapportagegegevens te verwijderen</value>
        </configuration>
        <configuration name="bad_delete_path">
          <value>Ongeldig pad voor verwijdering</value>
        </configuration>
        <configuration name="not_cached">
          <value>Het is niet mogelijk de cache voor het formulier in te stellen</value>
        </configuration>
        <configuration name="not_saved">
          <value>Het opslaan van de weergaveinstellingen is mislukt</value>
        </configuration>
        <configuration name="saved">
          <value>De weergaveinstellingen zijn opgeslagen</value>
        </configuration>
        <configuration name="not_generated">
          <value>Het aanmaken van de rapportage is mislukt</value>
        </configuration>
        <configuration name="not_updated">
          <value>Bijwerken van de waarden is niet mogelijk</value>
        </configuration>
        <configuration name="updated">
          <value>Bijgewerkte waarden</value>
        </configuration>
      </configurationGroup>
      <configurationGroup name="report_status">
        <configuration name="does_not_exist">
          <value>Bestaat niet</value>
        </configuration>
        <configuration name="not_generated">
          <value>Niet aangemaakt</value>
        </configuration>
        <configuration name="stale">
          <value>Vervallen</value>
        </configuration>
        <configuration name="failed">
          <value>Mislukt</value>
        </configuration>
        <configuration name="in_progress">
          <value>Wordt uitgevoerd</value>
        </configuration>
        <configuration name="generated">
          <value>Aangemaakt</value>
        </configuration>
      </configurationGroup>
      <configurationGroup name="headers">
        <configuration name="sum">
          <value>Som</value>
        </configuration>
        <configuration name="maximum"></configuration>
        <configuration name="minimum"></configuration>
        <configuration name="average">
          <value>Gemiddeld</value>
        </configuration>
        <configuration name="count">
          <value>Totaal</value>
        </configuration>
        <configuration name="count_distinct">
          <value>Totaal verschillende</value>
        </configuration>
      </configurationGroup>
    </configurationGroup>
    <configurationGroup name="tasks" path="/I2CE/tasks/task_description" locale="nl">
      <configuration name="custom_reports_can_access" locale="nl">
        <value>Staat minimale toegang toe tot het maatwerkrapportagesysteem</value>
      </configuration>
      <configuration name="custom_reports_delete" locale="nl">
        <value>Staat verwijderen van gegevens over maatwerkrapportages toe</value>
      </configuration>
      <configuration name="custom_reports_can_access_relationships" locale="nl">
        <value>Biedt toegang tot de maatwerkrapportagerelaties</value>
      </configuration>
      <configuration name="custom_reports_can_edit_relationships" locale="nl">
        <value>Maakt bewerken van de maatwerkrapportagerelaties mogelijk</value>
      </configuration>
      <configuration name="custom_reports_can_access_reports" locale="nl">
        <value>Biedt toegang tot de aangepaste rapportages</value>
      </configuration>
      <configuration name="custom_reports_can_edit_reports" locale="nl">
        <value>Maakt bewerken van de maatwerkrapportage mogelijk</value>
      </configuration>
      <configuration name="custom_reports_can_view_reportViews" locale="nl">
        <value>Maakt weergave van maatwerkrapportageweergaven mogelijk</value>
      </configuration>
      <configuration name="custom_reports_can_edit_reportViews" locale="nl">
        <value>Maakt bewerken van de maatwerkrapportageweergaven mogelijk</value>
      </configuration>
      <configuration name="custom_reports_admin" locale="nl">
        <value>Beheerder voor maatwerkrapportages. Kan alle taken uitvoeren die gekoppeld zijn aan de maatwerkrapportages</value>
      </configuration>
    </configurationGroup>
    <configurationGroup name="command_line">
      <configurationGroup name="show">
        <configurationGroup name="args">
          <configuration name="title" locale="nl">
            <value>Rapporten weergeven</value>
          </configuration>
        </configurationGroup>
      </configurationGroup>
    </configurationGroup>
    <configurationGroup name="page">
      <configurationGroup name="page_styles" path="/I2CE/template/page_styles">
        <configurationGroup name="customreport_config">
          <configurationGroup name="args">
            <configuration name="title" locale="nl">
              <value>Rapportages aanmaken</value>
            </configuration>
          </configurationGroup>
        </configurationGroup>
      </configurationGroup>
      <configurationGroup name="show">
        <configurationGroup name="args">
          <configuration name="title" locale="nl">
            <value>Rapporten weergeven</value>
          </configuration>
        </configurationGroup>
      </configurationGroup>
      <configurationGroup name="saveOptions">
        <configurationGroup name="args">
          <configuration name="title" locale="nl">
            <value>Rapporten weergeven</value>
          </configuration>
        </configurationGroup>
      </configurationGroup>
      <configurationGroup name="nodisplay">
        <configurationGroup name="args">
          <configuration name="title" locale="nl">
            <value>Geen geldige weergave</value>
          </configuration>
        </configurationGroup>
      </configurationGroup>
    </configurationGroup>
  </configurationGroup>
</I2CEConfiguration>